poetry_demo_datavault/__init__.py
poetry_demo_datavault/hello_world.py
poetry_demo_datavault-1.0.0.dist-info/METADATA
poetry_demo_datavault-1.0.0.dist-info/WHEEL
poetry_demo_datavault-1.0.0.dist-info/RECORD
