Metadata-Version: 2.1
Name: poetry-demo-datavault
Version: 1.0.0
Summary: 
Author: DVFrankieH
Author-email: frankie.homewood@business-thinking.com
Requires-Python: ==3.11.6
Classifier: Programming Language :: Python :: 3
Requires-Dist: pandas (>=2.1.1,<3.0.0)
